MfcRumenjiaocheng1TianShenruqianchuMfc/README.md
MfcRumenjiaocheng1TianShenruqianchuMfc/__init__.py
MfcRumenjiaocheng1TianShenruqianchuMfc/__main__.py
MfcRumenjiaocheng1TianShenruqianchuMfc/file.epub
MfcRumenjiaocheng1TianShenruqianchuMfc/index.html
MfcRumenjiaocheng1TianShenruqianchuMfc/css/__init__.py
MfcRumenjiaocheng1TianShenruqianchuMfc/css/annotations.css
MfcRumenjiaocheng1TianShenruqianchuMfc/css/main.css
MfcRumenjiaocheng1TianShenruqianchuMfc/css/normalize.css
MfcRumenjiaocheng1TianShenruqianchuMfc/css/popup.css
MfcRumenjiaocheng1TianShenruqianchuMfc/font/__init__.py
MfcRumenjiaocheng1TianShenruqianchuMfc/font/fontello.eot
MfcRumenjiaocheng1TianShenruqianchuMfc/font/fontello.svg
MfcRumenjiaocheng1TianShenruqianchuMfc/font/fontello.ttf
MfcRumenjiaocheng1TianShenruqianchuMfc/font/fontello.woff
MfcRumenjiaocheng1TianShenruqianchuMfc/img/__init__.py
MfcRumenjiaocheng1TianShenruqianchuMfc/img/annotator-glyph-sprite.png
MfcRumenjiaocheng1TianShenruqianchuMfc/img/annotator-icon-sprite.png
MfcRumenjiaocheng1TianShenruqianchuMfc/img/apple-touch-icon.png
MfcRumenjiaocheng1TianShenruqianchuMfc/img/cancelfullscreen.png
MfcRumenjiaocheng1TianShenruqianchuMfc/img/close.png
MfcRumenjiaocheng1TianShenruqianchuMfc/img/fullscreen.png
MfcRumenjiaocheng1TianShenruqianchuMfc/img/loader.gif
MfcRumenjiaocheng1TianShenruqianchuMfc/img/menu-icon.png
MfcRumenjiaocheng1TianShenruqianchuMfc/img/save.png
MfcRumenjiaocheng1TianShenruqianchuMfc/img/saved.png
MfcRumenjiaocheng1TianShenruqianchuMfc/img/settings-s.png
MfcRumenjiaocheng1TianShenruqianchuMfc/img/settings.png
MfcRumenjiaocheng1TianShenruqianchuMfc/img/star.png
MfcRumenjiaocheng1TianShenruqianchuMfc/js/__init__.py
MfcRumenjiaocheng1TianShenruqianchuMfc/js/epub.js
MfcRumenjiaocheng1TianShenruqianchuMfc/js/epub.min.js
MfcRumenjiaocheng1TianShenruqianchuMfc/js/epub.min.map
MfcRumenjiaocheng1TianShenruqianchuMfc/js/hooks.min.js
MfcRumenjiaocheng1TianShenruqianchuMfc/js/hooks.min.map
mfc_rumenjiaocheng_1_tian_shenruqianchu_mfc-2024.3.2.0.dist-info/METADATA
mfc_rumenjiaocheng_1_tian_shenruqianchu_mfc-2024.3.2.0.dist-info/WHEEL
mfc_rumenjiaocheng_1_tian_shenruqianchu_mfc-2024.3.2.0.dist-info/entry_points.txt
mfc_rumenjiaocheng_1_tian_shenruqianchu_mfc-2024.3.2.0.dist-info/top_level.txt
mfc_rumenjiaocheng_1_tian_shenruqianchu_mfc-2024.3.2.0.dist-info/RECORD
